PloidPy/__init__.py
PloidPy/binom_model.py
PloidPy/nbinom.py
PloidPy/ploidy_model.py
PloidPy/plot_read_data.py
PloidPy/process_bam.py
PloidPy_oaolayin-0.1.0.data/scripts/PloidPy
PloidPy_oaolayin-0.1.0.dist-info/LICENSE
PloidPy_oaolayin-0.1.0.dist-info/METADATA
PloidPy_oaolayin-0.1.0.dist-info/WHEEL
PloidPy_oaolayin-0.1.0.dist-info/top_level.txt
PloidPy_oaolayin-0.1.0.dist-info/RECORD
