Metadata-Version: 2.1
Name: PloidPy-oaolayin
Version: 0.1.0
Summary: Discrete mixture model based ploidy inference tool
Home-page: https://github.com/floutt/PloidPy
Author: Oluwatosin Olayinka
Author-email: oaolayin@live.unc.edu
License: UNKNOWN
Platform: UNKNOWN
Classifier: Programming Language :: Python :: 3
Classifier: License :: OSI Approved :: MIT License
Classifier: Operating System :: OS Independent
Requires-Python: >=3.6
